vsoa/__init__.py
vsoa/client.py
vsoa/events.py
vsoa/interface.py
vsoa/parser.py
vsoa/position.py
vsoa/server.py
vsoa/sockopt.py
vsoa/sslwork.py
vsoa/timer.py
vsoa/workqueue.py
vsoa-1.0.4.dist-info/licenses/LICENSE
vsoa-1.0.4.dist-info/METADATA
vsoa-1.0.4.dist-info/WHEEL
vsoa-1.0.4.dist-info/top_level.txt
vsoa-1.0.4.dist-info/RECORD
