Metadata-Version: 2.4
Name: vsoa
Version: 1.0.4
Summary: VSOA for Python
Author-email: ACOINFO <build@acoinfo.com>
License-Expression: Apache-2.0
Project-URL: Homepage, https://github.com/acoinfo/vsoa-python
Project-URL: Issues, https://github.com/acoinfo/vsoa-python/issues
Classifier: Programming Language :: Python :: 3
Classifier: Operating System :: OS Independent
Requires-Python: >=3.10
License-File: LICENSE
Dynamic: license-file
